{
  "file":"Kunoichi_tex.png",
  "frames":{
    "jump_13": {"frame": {"x":583,"y":269,"w":147,"h":205},"rotated": false, "trimmed": false },
    "idle_37": {"frame": {"x":3472,"y":540,"w":160,"h":240},"rotated": false, "trimmed": false },
    "run_15": {"frame": {"x":2995,"y":15,"w":166,"h":225},"rotated": false, "trimmed": false },
    "idle_27": {"frame": {"x":3673,"y":1086,"w":160,"h":240},"rotated": false, "trimmed": false },
    "idle_22": {"frame": {"x":1116,"y":1333,"w":160,"h":240},"rotated": false, "trimmed": false },
    "idle_67": {"frame": {"x":3479,"y":270,"w":160,"h":240},"rotated": false, "trimmed": false },
    "idle_9": {"frame": {"x":2809,"y":15,"w":160,"h":239},"rotated": false, "trimmed": false },
    "idle_31": {"frame": {"x":2405,"y":817,"w":160,"h":240},"rotated": false, "trimmed": false },
    "idle_40": {"frame": {"x":2743,"y":284,"w":160,"h":240},"rotated": false, "trimmed": false },
    "jump_27": {"frame": {"x":1441,"y":15,"w":174,"h":219},"rotated": false, "trimmed": false },
    "idle_55": {"frame": {"x":760,"y":1620,"w":160,"h":240},"rotated": false, "trimmed": false },
    "jump_6": {"frame": {"x":15,"y":784,"w":168,"h":232},"rotated": false, "trimmed": false },
    "idle_15": {"frame": {"x":580,"y":1551,"w":160,"h":239},"rotated": false, "trimmed": false },
    "idle_38": {"frame": {"x":3843,"y":277,"w":160,"h":240},"rotated": false, "trimmed": false },
    "idle_28": {"frame": {"x":1347,"y":1086,"w":160,"h":240},"rotated": false, "trimmed": false },
    "idle_23": {"frame": {"x":1116,"y":1603,"w":160,"h":240},"rotated": false, "trimmed": false },
    "run_19": {"frame": {"x":2431,"y":15,"w":162,"h":232},"rotated": false, "trimmed": false },
    "idle_4": {"frame": {"x":583,"y":811,"w":160,"h":240},"rotated": false, "trimmed": false },
    "run_20": {"frame": {"x":3786,"y":15,"w":160,"h":232},"rotated": false, "trimmed": false },
    "idle_66": {"frame": {"x":1863,"y":817,"w":160,"h":240},"rotated": false, "trimmed": false },
    "jump_19": {"frame": {"x":221,"y":15,"w":180,"h":221},"rotated": false, "trimmed": false },
    "jump_24": {"frame": {"x":640,"y":15,"w":173,"h":224},"rotated": false, "trimmed": false },
    "idle_26": {"frame": {"x":1650,"y":1357,"w":160,"h":241},"rotated": false, "trimmed": false },
    "idle_20": {"frame": {"x":938,"y":1350,"w":160,"h":240},"rotated": false, "trimmed": false },
    "idle_25": {"frame": {"x":1649,"y":1628,"w":160,"h":240},"rotated": false, "trimmed": false },
    "idle_53": {"frame": {"x":2421,"y":1087,"w":160,"h":239},"rotated": false, "trimmed": false },
    "jump_3": {"frame": {"x":2383,"y":1356,"w":169,"h":208},"rotated": false, "trimmed": false },
    "jump_15": {"frame": {"x":401,"y":267,"w":160,"h":204},"rotated": false, "trimmed": false },
    "jump_0": {"frame": {"x":951,"y":1086,"w":166,"h":217},"rotated": false, "trimmed": false },
    "idle_12": {"frame": {"x":1499,"y":817,"w":160,"h":239},"rotated": false, "trimmed": false },
    "run_0": {"frame": {"x":3533,"y":1356,"w":146,"h":232},"rotated": false, "trimmed": false },
    "jump_4": {"frame": {"x":2945,"y":811,"w":169,"h":214},"rotated": false, "trimmed": false },
    "run_17": {"frame": {"x":1645,"y":15,"w":165,"h":230},"rotated": false, "trimmed": false },
    "run_23": {"frame": {"x":2202,"y":1356,"w":151,"h":232},"rotated": false, "trimmed": false },
    "run_16": {"frame": {"x":2039,"y":15,"w":166,"h":227},"rotated": false, "trimmed": false },
    "jump_16": {"frame": {"x":3156,"y":1341,"w":164,"h":208},"rotated": false, "trimmed": false },
    "jump_12": {"frame": {"x":583,"y":504,"w":144,"h":204},"rotated": false, "trimmed": false },
    "idle_29": {"frame": {"x":1705,"y":1087,"w":160,"h":240},"rotated": false, "trimmed": false },
    "idle_45": {"frame": {"x":2185,"y":272,"w":160,"h":239},"rotated": false, "trimmed": false },
    "jump_20": {"frame": {"x":431,"y":15,"w":179,"h":222},"rotated": false, "trimmed": false },
    "idle_19": {"frame": {"x":2600,"y":1087,"w":160,"h":239},"rotated": false, "trimmed": false },
    "idle_59": {"frame": {"x":2025,"y":1357,"w":160,"h":240},"rotated": false, "trimmed": false },
    "run_10": {"frame": {"x":1247,"y":15,"w":164,"h":233},"rotated": false, "trimmed": false },
    "jump_11": {"frame": {"x":222,"y":545,"w":151,"h":209},"rotated": false, "trimmed": false },
    "run_2": {"frame": {"x":220,"y":272,"w":151,"h":218},"rotated": false, "trimmed": false },
    "run_18": {"frame": {"x":15,"y":1572,"w":165,"h":233},"rotated": false, "trimmed": false },
    "idle_18": {"frame": {"x":2779,"y":1087,"w":160,"h":239},"rotated": false, "trimmed": false },
    "jump_21": {"frame": {"x":15,"y":530,"w":177,"h":224},"rotated": false, "trimmed": false },
    "idle_35": {"frame": {"x":3290,"y":530,"w":160,"h":240},"rotated": false, "trimmed": false },
    "jump_25": {"frame": {"x":1040,"y":15,"w":177,"h":217},"rotated": false, "trimmed": false },
    "idle_48": {"frame": {"x":3515,"y":817,"w":160,"h":239},"rotated": false, "trimmed": false },
    "jump_8": {"frame": {"x":211,"y":1291,"w":163,"h":222},"rotated": false, "trimmed": false },
    "idle_5": {"frame": {"x":3108,"y":270,"w":160,"h":241},"rotated": false, "trimmed": false },
    "idle_50": {"frame": {"x":2958,"y":1055,"w":160,"h":239},"rotated": false, "trimmed": false },
    "idle_54": {"frame": {"x":938,"y":1620,"w":160,"h":240},"rotated": false, "trimmed": false },
    "idle_47": {"frame": {"x":3695,"y":817,"w":160,"h":239},"rotated": false, "trimmed": false },
    "jump_14": {"frame": {"x":403,"y":501,"w":160,"h":204},"rotated": false, "trimmed": false },
    "idle_65": {"frame": {"x":2585,"y":817,"w":160,"h":240},"rotated": false, "trimmed": false },
    "idle_58": {"frame": {"x":1294,"y":1626,"w":160,"h":240},"rotated": false, "trimmed": false },
    "idle_21": {"frame": {"x":3495,"y":1086,"w":160,"h":240},"rotated": false, "trimmed": false },
    "idle_32": {"frame": {"x":2044,"y":817,"w":160,"h":240},"rotated": false, "trimmed": false },
    "idle_39": {"frame": {"x":2926,"y":284,"w":160,"h":241},"rotated": false, "trimmed": false },
    "idle_36": {"frame": {"x":3661,"y":277,"w":160,"h":240},"rotated": false, "trimmed": false },
    "run_8": {"frame": {"x":2369,"y":277,"w":161,"h":229},"rotated": false, "trimmed": false },
    "idle_62": {"frame": {"x":1884,"y":1087,"w":160,"h":240},"rotated": false, "trimmed": false },
    "jump_28": {"frame": {"x":843,"y":15,"w":167,"h":230},"rotated": false, "trimmed": false },
    "idle_24": {"frame": {"x":1294,"y":1356,"w":160,"h":240},"rotated": false, "trimmed": false },
    "run_4": {"frame": {"x":2781,"y":1356,"w":160,"h":226},"rotated": false, "trimmed": false },
    "run_3": {"frame": {"x":3350,"y":1356,"w":153,"h":222},"rotated": false, "trimmed": false },
    "idle_63": {"frame": {"x":1526,"y":1086,"w":160,"h":240},"rotated": false, "trimmed": false },
    "jump_5": {"frame": {"x":1840,"y":15,"w":169,"h":224},"rotated": false, "trimmed": false },
    "run_22": {"frame": {"x":3330,"y":810,"w":160,"h":232},"rotated": false, "trimmed": false },
    "idle_61": {"frame": {"x":3851,"y":1086,"w":160,"h":240},"rotated": false, "trimmed": false },
    "idle_2": {"frame": {"x":3836,"y":547,"w":160,"h":240},"rotated": false, "trimmed": false },
    "jump_7": {"frame": {"x":2235,"y":15,"w":166,"h":227},"rotated": false, "trimmed": false },
    "run_7": {"frame": {"x":3290,"y":270,"w":159,"h":230},"rotated": false, "trimmed": false },
    "run_14": {"frame": {"x":3387,"y":15,"w":166,"h":225},"rotated": false, "trimmed": false },
    "run_12": {"frame": {"x":15,"y":1310,"w":166,"h":232},"rotated": false, "trimmed": false },
    "idle_41": {"frame": {"x":1441,"y":264,"w":160,"h":240},"rotated": false, "trimmed": false },
    "idle_33": {"frame": {"x":3108,"y":541,"w":160,"h":240},"rotated": false, "trimmed": false },
    "jump_17": {"frame": {"x":1147,"y":1086,"w":170,"h":212},"rotated": false, "trimmed": false },
    "idle_44": {"frame": {"x":210,"y":1572,"w":160,"h":239},"rotated": false, "trimmed": false },
    "run_5": {"frame": {"x":3144,"y":811,"w":156,"h":231},"rotated": false, "trimmed": false },
    "run_13": {"frame": {"x":3191,"y":15,"w":166,"h":225},"rotated": false, "trimmed": false },
    "idle_3": {"frame": {"x":3654,"y":547,"w":160,"h":240},"rotated": false, "trimmed": false },
    "run_6": {"frame": {"x":404,"y":1291,"w":157,"h":230},"rotated": false, "trimmed": false },
    "idle_0": {"frame": {"x":1317,"y":817,"w":160,"h":239},"rotated": false, "trimmed": false },
    "idle_6": {"frame": {"x":2560,"y":284,"w":160,"h":240},"rotated": false, "trimmed": false },
    "idle_49": {"frame": {"x":591,"y":1081,"w":160,"h":239},"rotated": false, "trimmed": false },
    "idle_56": {"frame": {"x":1472,"y":1356,"w":160,"h":240},"rotated": false, "trimmed": false },
    "idle_60": {"frame": {"x":1472,"y":1626,"w":160,"h":241},"rotated": false, "trimmed": false },
    "idle_43": {"frame": {"x":2623,"y":15,"w":160,"h":239},"rotated": false, "trimmed": false },
    "idle_52": {"frame": {"x":3316,"y":1072,"w":160,"h":239},"rotated": false, "trimmed": false },
    "idle_16": {"frame": {"x":2242,"y":1087,"w":160,"h":239},"rotated": false, "trimmed": false },
    "run_11": {"frame": {"x":15,"y":1046,"w":165,"h":234},"rotated": false, "trimmed": false },
    "idle_57": {"frame": {"x":760,"y":1350,"w":160,"h":240},"rotated": false, "trimmed": false },
    "idle_46": {"frame": {"x":1135,"y":817,"w":160,"h":239},"rotated": false, "trimmed": false },
    "idle_8": {"frame": {"x":213,"y":784,"w":160,"h":239},"rotated": false, "trimmed": false },
    "jump_10": {"frame": {"x":3888,"y":1356,"w":156,"h":213},"rotated": false, "trimmed": false },
    "jump_23": {"frame": {"x":15,"y":272,"w":175,"h":228},"rotated": false, "trimmed": false },
    "idle_51": {"frame": {"x":3137,"y":1072,"w":160,"h":239},"rotated": false, "trimmed": false },
    "jump_9": {"frame": {"x":2966,"y":1341,"w":160,"h":218},"rotated": false, "trimmed": false },
    "jump_26": {"frame": {"x":210,"y":1053,"w":175,"h":208},"rotated": false, "trimmed": false },
    "jump_18": {"frame": {"x":3583,"y":15,"w":173,"h":216},"rotated": false, "trimmed": false },
    "jump_1": {"frame": {"x":1827,"y":1357,"w":168,"h":212},"rotated": false, "trimmed": false },
    "idle_64": {"frame": {"x":2225,"y":817,"w":160,"h":240},"rotated": false, "trimmed": false },
    "run_1": {"frame": {"x":3709,"y":1356,"w":149,"h":226},"rotated": false, "trimmed": false },
    "idle_14": {"frame": {"x":771,"y":1081,"w":160,"h":239},"rotated": false, "trimmed": false },
    "jump_2": {"frame": {"x":2582,"y":1356,"w":169,"h":208},"rotated": false, "trimmed": false },
    "idle_10": {"frame": {"x":398,"y":784,"w":160,"h":239},"rotated": false, "trimmed": false },
    "run_9": {"frame": {"x":1809,"y":275,"w":162,"h":228},"rotated": false, "trimmed": false },
    "idle_11": {"frame": {"x":2001,"y":272,"w":160,"h":239},"rotated": false, "trimmed": false },
    "jump_22": {"frame": {"x":15,"y":15,"w":176,"h":227},"rotated": false, "trimmed": false },
    "idle_17": {"frame": {"x":2063,"y":1087,"w":160,"h":239},"rotated": false, "trimmed": false },
    "run_21": {"frame": {"x":947,"y":817,"w":158,"h":231},"rotated": false, "trimmed": false },
    "idle_30": {"frame": {"x":2765,"y":817,"w":160,"h":240},"rotated": false, "trimmed": false },
    "idle_42": {"frame": {"x":395,"y":1572,"w":160,"h":239},"rotated": false, "trimmed": false },
    "idle_13": {"frame": {"x":3875,"y":817,"w":160,"h":239},"rotated": false, "trimmed": false },
    "idle_7": {"frame": {"x":1625,"y":275,"w":160,"h":240},"rotated": false, "trimmed": false },
    "idle_1": {"frame": {"x":765,"y":811,"w":160,"h":240},"rotated": false, "trimmed": false },
    "idle_34": {"frame": {"x":1681,"y":817,"w":160,"h":239},"rotated": false, "trimmed": false }
  },
  "meta": { "image": "Kunoichi_tex.png" }
}